royal_mail_click_and_drop/__init__.py
royal_mail_click_and_drop/api_client.py
royal_mail_click_and_drop/api_response.py
royal_mail_click_and_drop/config.py
royal_mail_click_and_drop/configuration.py
royal_mail_click_and_drop/exceptions.py
royal_mail_click_and_drop/py.typed
royal_mail_click_and_drop/rest.py
royal_mail_click_and_drop/api/__init__.py
royal_mail_click_and_drop/api/labels_api.py
royal_mail_click_and_drop/api/manifests_api.py
royal_mail_click_and_drop/api/orders_api.py
royal_mail_click_and_drop/api/version_api.py
royal_mail_click_and_drop/models/__init__.py
royal_mail_click_and_drop/models/address.py
royal_mail_click_and_drop/models/base.py
royal_mail_click_and_drop/models/billing_details_request.py
royal_mail_click_and_drop/models/create_order_error_response.py
royal_mail_click_and_drop/models/create_order_label_error_response.py
royal_mail_click_and_drop/models/create_order_response.py
royal_mail_click_and_drop/models/create_orders_request.py
royal_mail_click_and_drop/models/create_orders_response.py
royal_mail_click_and_drop/models/delete_orders_resource.py
royal_mail_click_and_drop/models/deleted_order_info.py
royal_mail_click_and_drop/models/dimensions_request.py
royal_mail_click_and_drop/models/error_response.py
royal_mail_click_and_drop/models/failed_order_response.py
royal_mail_click_and_drop/models/get_order_details_resource.py
royal_mail_click_and_drop/models/get_order_info_resource.py
royal_mail_click_and_drop/models/get_order_line_result.py
royal_mail_click_and_drop/models/get_orders_details_response.py
royal_mail_click_and_drop/models/get_orders_response.py
royal_mail_click_and_drop/models/get_postal_details_result.py
royal_mail_click_and_drop/models/get_shipping_details_result.py
royal_mail_click_and_drop/models/get_tag_details_result.py
royal_mail_click_and_drop/models/get_version_resource.py
royal_mail_click_and_drop/models/importer.py
royal_mail_click_and_drop/models/label_generation_request.py
royal_mail_click_and_drop-0.0.10.dist-info/METADATA
royal_mail_click_and_drop-0.0.10.dist-info/WHEEL
royal_mail_click_and_drop-0.0.10.dist-info/top_level.txt
royal_mail_click_and_drop-0.0.10.dist-info/RECORD
