Metadata-Version: 2.4
Name: royal-mail-click-and-drop
Version: 0.0.10
Summary: Royal Mail Click and Drop Client
Author-email: pawrequest <royal_mail+pawrequest@users.noreply.github.com>
License-Expression: MIT
Requires-Python: >=3.12
Requires-Dist: urllib3<3.0.0,>=2.1.0
Requires-Dist: python-dateutil>=2.8.2
Requires-Dist: pydantic>=2
Requires-Dist: typing-extensions>=4.7.1
Requires-Dist: pydantic-settings>=2.11.0
Requires-Dist: loguru>=0.7.3
